cachefn/__init__.py
cachefn/analytics/__init__.py
cachefn/analytics/stats.py
cachefn/core/__init__.py
cachefn/core/cache.py
cachefn/core/events.py
cachefn/core/types.py
cachefn/memoization/__init__.py
cachefn/memoization/memoize.py
cachefn/storage/__init__.py
cachefn/storage/memory_storage.py
cachefn/utils/__init__.py
cachefn/utils/hash.py
cachefn/utils/pattern.py
cachefn/utils/serialize.py
cachefn/utils/ttl.py
cachefn-0.0.1.dist-info/METADATA
cachefn-0.0.1.dist-info/WHEEL
cachefn-0.0.1.dist-info/licenses/LICENSE
cachefn-0.0.1.dist-info/RECORD
