Metadata-Version: 2.4
Name: cachefn
Version: 0.0.1
Summary: Self-hosted caching solution for Python applications
Project-URL: Documentation, https://docs.superfunctions.dev/cachefn
Project-URL: Repository, https://github.com/21nCo/super-functions
Project-URL: Issues, https://github.com/21nCo/super-functions/issues
Author: 21n
License-Expression: Apache-2.0
License-File: LICENSE
Keywords: cache,caching,memoization,superfunctions
Classifier: Development Status :: 3 - Alpha
Classifier: Intended Audience :: Developers
Classifier: License :: OSI Approved :: Apache Software License
Classifier: Programming Language :: Python :: 3
Classifier: Programming Language :: Python :: 3.10
Classifier: Programming Language :: Python :: 3.11
Classifier: Programming Language :: Python :: 3.12
Classifier: Topic :: Software Development :: Libraries :: Python Modules
Requires-Python: >=3.10
Requires-Dist: pydantic>=2.5.0
Provides-Extra: dev
Requires-Dist: black>=23.11.0; extra == 'dev'
Requires-Dist: mypy>=1.7.0; extra == 'dev'
Requires-Dist: pytest-asyncio>=0.21.0; extra == 'dev'
Requires-Dist: pytest-cov>=4.1.0; extra == 'dev'
Requires-Dist: pytest>=7.4.0; extra == 'dev'
Requires-Dist: ruff>=0.1.6; extra == 'dev'
Provides-Extra: fastapi
Requires-Dist: fastapi>=0.104.0; extra == 'fastapi'
Provides-Extra: flask
Requires-Dist: flask>=3.0.0; extra == 'flask'
